{
  "name": "Gardnerville Ranchos",
  "state": "Nevada",
  "state_abbr": "NV",
  "county": "Douglas",
  "population": 11760,
  "slug": "gardnerville-ranchos-nv",
  "businesses": [
    {
      "name": "Desert Employment Agency Inc",
      "category": "Employment Agency",
      "address": "Gardnerville Ranchos, NV",
      "phone": "",
      "email": "",
      "website": "",
      "hours": "",
      "rating": null,
      "review_count": null,
      "claimed": false,
      "featured": false
    },
    {
      "name": "Douglas Movie Theater Inc",
      "category": "Movie Theater",
      "address": "Gardnerville Ranchos, NV",
      "phone": "",
      "email": "",
      "website": "",
      "hours": "",
      "rating": null,
      "review_count": null,
      "claimed": false,
      "featured": false
    },
    {
      "name": "Douglas Car Wash LLC",
      "category": "Car Wash",
      "address": "Gardnerville Ranchos, NV",
      "phone": "",
      "email": "",
      "website": "",
      "hours": "",
      "rating": null,
      "review_count": null,
      "claimed": false,
      "featured": false
    },
    {
      "name": "Valley Siding Group",
      "category": "Siding",
      "address": "Gardnerville Ranchos, NV",
      "phone": "",
      "email": "",
      "website": "",
      "hours": "",
      "rating": null,
      "review_count": null,
      "claimed": false,
      "featured": false
    },
    {
      "name": "Sagebrush Gym Services",
      "category": "Gym",
      "address": "Gardnerville Ranchos, NV",
      "phone": "",
      "email": "",
      "website": "",
      "hours": "",
      "rating": null,
      "review_count": null,
      "claimed": false,
      "featured": false
    },
    {
      "name": "Gardnerville Ranchos Pest Control LLC",
      "category": "Pest Control",
      "address": "Gardnerville Ranchos, NV",
      "phone": "",
      "email": "",
      "website": "",
      "hours": "",
      "rating": null,
      "review_count": null,
      "claimed": false,
      "featured": false
    },
    {
      "name": "Silver State Toy Store Services",
      "category": "Toy Store",
      "address": "Gardnerville Ranchos, NV",
      "phone": "",
      "email": "",
      "website": "",
      "hours": "",
      "rating": null,
      "review_count": null,
      "claimed": false,
      "featured": false
    },
    {
      "name": "Frontier Laundromat Co",
      "category": "Laundromat",
      "address": "Gardnerville Ranchos, NV",
      "phone": "",
      "email": "",
      "website": "",
      "hours": "",
      "rating": null,
      "review_count": null,
      "claimed": false,
      "featured": false
    },
    {
      "name": "Douglas Liquor Store Plus",
      "category": "Liquor Store",
      "address": "Gardnerville Ranchos, NV",
      "phone": "",
      "email": "",
      "website": "",
      "hours": "",
      "rating": null,
      "review_count": null,
      "claimed": false,
      "featured": false
    },
    {
      "name": "Douglas HVAC Services",
      "category": "HVAC",
      "address": "Gardnerville Ranchos, NV",
      "phone": "",
      "email": "",
      "website": "",
      "hours": "",
      "rating": null,
      "review_count": null,
      "claimed": false,
      "featured": false
    },
    {
      "name": "Battle Born Hotel of Gardnerville Ranchos",
      "category": "Hotel",
      "address": "Gardnerville Ranchos, NV",
      "phone": "",
      "email": "",
      "website": "",
      "hours": "",
      "rating": null,
      "review_count": null,
      "claimed": false,
      "featured": false
    },
    {
      "name": "Frontier Daycare Pro",
      "category": "Daycare",
      "address": "Gardnerville Ranchos, NV",
      "phone": "",
      "email": "",
      "website": "",
      "hours": "",
      "rating": null,
      "review_count": null,
      "claimed": false,
      "featured": false
    },
    {
      "name": "Heritage Outdoor Store Inc",
      "category": "Outdoor Store",
      "address": "Gardnerville Ranchos, NV",
      "phone": "",
      "email": "",
      "website": "",
      "hours": "",
      "rating": null,
      "review_count": null,
      "claimed": false,
      "featured": false
    },
    {
      "name": "Douglas Sporting Goods Pro",
      "category": "Sporting Goods",
      "address": "Gardnerville Ranchos, NV",
      "phone": "",
      "email": "",
      "website": "",
      "hours": "",
      "rating": null,
      "review_count": null,
      "claimed": false,
      "featured": false
    },
    {
      "name": "Douglas Pet Store Services",
      "category": "Pet Store",
      "address": "Gardnerville Ranchos, NV",
      "phone": "",
      "email": "",
      "website": "",
      "hours": "",
      "rating": null,
      "review_count": null,
      "claimed": false,
      "featured": false
    },
    {
      "name": "Douglas Pool Service Solutions",
      "category": "Pool Service",
      "address": "Gardnerville Ranchos, NV",
      "phone": "",
      "email": "",
      "website": "",
      "hours": "",
      "rating": null,
      "review_count": null,
      "claimed": false,
      "featured": false
    },
    {
      "name": "Nevada Church Express",
      "category": "Church",
      "address": "Gardnerville Ranchos, NV",
      "phone": "",
      "email": "",
      "website": "",
      "hours": "",
      "rating": null,
      "review_count": null,
      "claimed": false,
      "featured": false
    },
    {
      "name": "Gardnerville Ranchos Golf Course Solutions",
      "category": "Golf Course",
      "address": "Gardnerville Ranchos, NV",
      "phone": "",
      "email": "",
      "website": "",
      "hours": "",
      "rating": null,
      "review_count": null,
      "claimed": false,
      "featured": false
    },
    {
      "name": "Battle Born School Center",
      "category": "School",
      "address": "Gardnerville Ranchos, NV",
      "phone": "",
      "email": "",
      "website": "",
      "hours": "",
      "rating": null,
      "review_count": null,
      "claimed": false,
      "featured": false
    },
    {
      "name": "Gardnerville Ranchos Concrete Solutions",
      "category": "Concrete",
      "address": "Gardnerville Ranchos, NV",
      "phone": "",
      "email": "",
      "website": "",
      "hours": "",
      "rating": null,
      "review_count": null,
      "claimed": false,
      "featured": false
    },
    {
      "name": "Douglas Chiropractor Co",
      "category": "Chiropractor",
      "address": "Gardnerville Ranchos, NV",
      "phone": "",
      "email": "",
      "website": "",
      "hours": "",
      "rating": null,
      "review_count": null,
      "claimed": false,
      "featured": false
    },
    {
      "name": "Sierra Barber Shop of Gardnerville Ranchos",
      "category": "Barber Shop",
      "address": "Gardnerville Ranchos, NV",
      "phone": "",
      "email": "",
      "website": "",
      "hours": "",
      "rating": null,
      "review_count": null,
      "claimed": false,
      "featured": false
    },
    {
      "name": "Pioneer Tractor Dealer LLC",
      "category": "Tractor Dealer",
      "address": "Gardnerville Ranchos, NV",
      "phone": "",
      "email": "",
      "website": "",
      "hours": "",
      "rating": null,
      "review_count": null,
      "claimed": false,
      "featured": false
    },
    {
      "name": "Douglas Gift Shop LLC",
      "category": "Gift Shop",
      "address": "Gardnerville Ranchos, NV",
      "phone": "",
      "email": "",
      "website": "",
      "hours": "",
      "rating": null,
      "review_count": null,
      "claimed": false,
      "featured": false
    },
    {
      "name": "Wild West Dry Cleaner of Gardnerville Ranchos",
      "category": "Dry Cleaner",
      "address": "Gardnerville Ranchos, NV",
      "phone": "",
      "email": "",
      "website": "",
      "hours": "",
      "rating": null,
      "review_count": null,
      "claimed": false,
      "featured": false
    },
    {
      "name": "Frontier Appliance Store Inc",
      "category": "Appliance Store",
      "address": "Gardnerville Ranchos, NV",
      "phone": "",
      "email": "",
      "website": "",
      "hours": "",
      "rating": null,
      "review_count": null,
      "claimed": false,
      "featured": false
    },
    {
      "name": "Gardnerville Ranchos Bar Plus",
      "category": "Bar",
      "address": "Gardnerville Ranchos, NV",
      "phone": "",
      "email": "",
      "website": "",
      "hours": "",
      "rating": null,
      "review_count": null,
      "claimed": false,
      "featured": false
    },
    {
      "name": "Gardnerville Ranchos Music Store Pro",
      "category": "Music Store",
      "address": "Gardnerville Ranchos, NV",
      "phone": "",
      "email": "",
      "website": "",
      "hours": "",
      "rating": null,
      "review_count": null,
      "claimed": false,
      "featured": false
    },
    {
      "name": "Gardnerville Ranchos Tailor Pro",
      "category": "Tailor",
      "address": "Gardnerville Ranchos, NV",
      "phone": "",
      "email": "",
      "website": "",
      "hours": "",
      "rating": null,
      "review_count": null,
      "claimed": false,
      "featured": false
    },
    {
      "name": "Douglas Security Company Services",
      "category": "Security Company",
      "address": "Gardnerville Ranchos, NV",
      "phone": "",
      "email": "",
      "website": "",
      "hours": "",
      "rating": null,
      "review_count": null,
      "claimed": false,
      "featured": false
    },
    {
      "name": "Douglas Optometrist Inc",
      "category": "Optometrist",
      "address": "Gardnerville Ranchos, NV",
      "phone": "",
      "email": "",
      "website": "",
      "hours": "",
      "rating": null,
      "review_count": null,
      "claimed": false,
      "featured": false
    },
    {
      "name": "Desert Casino Express",
      "category": "Casino",
      "address": "Gardnerville Ranchos, NV",
      "phone": "",
      "email": "",
      "website": "",
      "hours": "",
      "rating": null,
      "review_count": null,
      "claimed": false,
      "featured": false
    },
    {
      "name": "Douglas Painting Co",
      "category": "Painting",
      "address": "Gardnerville Ranchos, NV",
      "phone": "",
      "email": "",
      "website": "",
      "hours": "",
      "rating": null,
      "review_count": null,
      "claimed": false,
      "featured": false
    },
    {
      "name": "Silver State Farm Supply of Gardnerville Ranchos",
      "category": "Farm Supply",
      "address": "Gardnerville Ranchos, NV",
      "phone": "",
      "email": "",
      "website": "",
      "hours": "",
      "rating": null,
      "review_count": null,
      "claimed": false,
      "featured": false
    },
    {
      "name": "Gardnerville Ranchos Landscaping LLC",
      "category": "Landscaping",
      "address": "Gardnerville Ranchos, NV",
      "phone": "",
      "email": "",
      "website": "",
      "hours": "",
      "rating": null,
      "review_count": null,
      "claimed": false,
      "featured": false
    },
    {
      "name": "Gardnerville Ranchos Photography Studio Pro",
      "category": "Photography Studio",
      "address": "Gardnerville Ranchos, NV",
      "phone": "",
      "email": "",
      "website": "",
      "hours": "",
      "rating": null,
      "review_count": null,
      "claimed": false,
      "featured": false
    },
    {
      "name": "Silver State Law Office Pro",
      "category": "Law Office",
      "address": "Gardnerville Ranchos, NV",
      "phone": "",
      "email": "",
      "website": "",
      "hours": "",
      "rating": null,
      "review_count": null,
      "claimed": false,
      "featured": false
    },
    {
      "name": "Gardnerville Ranchos Bowling Alley LLC",
      "category": "Bowling Alley",
      "address": "Gardnerville Ranchos, NV",
      "phone": "",
      "email": "",
      "website": "",
      "hours": "",
      "rating": null,
      "review_count": null,
      "claimed": false,
      "featured": false
    },
    {
      "name": "Douglas Storage Facility Plus",
      "category": "Storage Facility",
      "address": "Gardnerville Ranchos, NV",
      "phone": "",
      "email": "",
      "website": "",
      "hours": "",
      "rating": null,
      "review_count": null,
      "claimed": false,
      "featured": false
    },
    {
      "name": "Nevada Pawn Shop Services",
      "category": "Pawn Shop",
      "address": "Gardnerville Ranchos, NV",
      "phone": "",
      "email": "",
      "website": "",
      "hours": "",
      "rating": null,
      "review_count": null,
      "claimed": false,
      "featured": false
    },
    {
      "name": "Gardnerville Ranchos Bed and Breakfast Co",
      "category": "Bed and Breakfast",
      "address": "Gardnerville Ranchos, NV",
      "phone": "",
      "email": "",
      "website": "",
      "hours": "",
      "rating": null,
      "review_count": null,
      "claimed": false,
      "featured": false
    },
    {
      "name": "Gardnerville Ranchos Gas Station Express",
      "category": "Gas Station",
      "address": "Gardnerville Ranchos, NV",
      "phone": "",
      "email": "",
      "website": "",
      "hours": "",
      "rating": null,
      "review_count": null,
      "claimed": false,
      "featured": false
    },
    {
      "name": "Gardnerville Ranchos Marina Plus",
      "category": "Marina",
      "address": "Gardnerville Ranchos, NV",
      "phone": "",
      "email": "",
      "website": "",
      "hours": "",
      "rating": null,
      "review_count": null,
      "claimed": false,
      "featured": false
    },
    {
      "name": "Gardnerville Ranchos Wedding Chapel Inc",
      "category": "Wedding Chapel",
      "address": "Gardnerville Ranchos, NV",
      "phone": "",
      "email": "",
      "website": "",
      "hours": "",
      "rating": null,
      "review_count": null,
      "claimed": false,
      "featured": false
    },
    {
      "name": "Desert Auto Repair of Gardnerville Ranchos",
      "category": "Auto Repair",
      "address": "Gardnerville Ranchos, NV",
      "phone": "",
      "email": "",
      "website": "",
      "hours": "",
      "rating": null,
      "review_count": null,
      "claimed": false,
      "featured": false
    },
    {
      "name": "Douglas Martial Arts LLC",
      "category": "Martial Arts",
      "address": "Gardnerville Ranchos, NV",
      "phone": "",
      "email": "",
      "website": "",
      "hours": "",
      "rating": null,
      "review_count": null,
      "claimed": false,
      "featured": false
    },
    {
      "name": "Valley Printing Shop Co",
      "category": "Printing Shop",
      "address": "Gardnerville Ranchos, NV",
      "phone": "",
      "email": "",
      "website": "",
      "hours": "",
      "rating": null,
      "review_count": null,
      "claimed": false,
      "featured": false
    },
    {
      "name": "Wild West Roofing Express",
      "category": "Roofing",
      "address": "Gardnerville Ranchos, NV",
      "phone": "",
      "email": "",
      "website": "",
      "hours": "",
      "rating": null,
      "review_count": null,
      "claimed": false,
      "featured": false
    },
    {
      "name": "Gardnerville Ranchos Bank Inc",
      "category": "Bank",
      "address": "Gardnerville Ranchos, NV",
      "phone": "",
      "email": "",
      "website": "",
      "hours": "",
      "rating": null,
      "review_count": null,
      "claimed": false,
      "featured": false
    },
    {
      "name": "Douglas Antique Store Services",
      "category": "Antique Store",
      "address": "Gardnerville Ranchos, NV",
      "phone": "",
      "email": "",
      "website": "",
      "hours": "",
      "rating": null,
      "review_count": null,
      "claimed": false,
      "featured": false
    }
  ]
}