{
  "name": "Lewis and Clark Village",
  "state": "Missouri",
  "state_abbr": "MO",
  "county": "St. Charles",
  "population": 1500,
  "slug": "lewis-and-clark-village-mo",
  "businesses": [
    {
      "name": "Midwest Toy Store of Lewis and Clark Village",
      "category": "Toy Store",
      "address": "Lewis and Clark Village, MO",
      "phone": "",
      "email": "",
      "website": "",
      "hours": "",
      "rating": null,
      "review_count": null,
      "claimed": false,
      "featured": false
    },
    {
      "name": "Valley School of Lewis and Clark Village",
      "category": "School",
      "address": "Lewis and Clark Village, MO",
      "phone": "",
      "email": "",
      "website": "",
      "hours": "",
      "rating": null,
      "review_count": null,
      "claimed": false,
      "featured": false
    },
    {
      "name": "Lake Jewelry Store Express",
      "category": "Jewelry Store",
      "address": "Lewis and Clark Village, MO",
      "phone": "",
      "email": "",
      "website": "",
      "hours": "",
      "rating": null,
      "review_count": null,
      "claimed": false,
      "featured": false
    },
    {
      "name": "Lake HVAC of Lewis and Clark Village",
      "category": "HVAC",
      "address": "Lewis and Clark Village, MO",
      "phone": "",
      "email": "",
      "website": "",
      "hours": "",
      "rating": null,
      "review_count": null,
      "claimed": false,
      "featured": false
    },
    {
      "name": "Lewis and Clark Village Bed and Breakfast Inc",
      "category": "Bed and Breakfast",
      "address": "Lewis and Clark Village, MO",
      "phone": "",
      "email": "",
      "website": "",
      "hours": "",
      "rating": null,
      "review_count": null,
      "claimed": false,
      "featured": false
    },
    {
      "name": "St. Charles Nail Salon Services",
      "category": "Nail Salon",
      "address": "Lewis and Clark Village, MO",
      "phone": "",
      "email": "",
      "website": "",
      "hours": "",
      "rating": null,
      "review_count": null,
      "claimed": false,
      "featured": false
    },
    {
      "name": "Gateway Arch Pest Control of Lewis and Clark Village",
      "category": "Pest Control",
      "address": "Lewis and Clark Village, MO",
      "phone": "",
      "email": "",
      "website": "",
      "hours": "",
      "rating": null,
      "review_count": null,
      "claimed": false,
      "featured": false
    },
    {
      "name": "Lewis and Clark Village Yoga Studio Plus",
      "category": "Yoga Studio",
      "address": "Lewis and Clark Village, MO",
      "phone": "",
      "email": "",
      "website": "",
      "hours": "",
      "rating": null,
      "review_count": null,
      "claimed": false,
      "featured": false
    },
    {
      "name": "Midwest Staffing Agency Inc",
      "category": "Staffing Agency",
      "address": "Lewis and Clark Village, MO",
      "phone": "",
      "email": "",
      "website": "",
      "hours": "",
      "rating": null,
      "review_count": null,
      "claimed": false,
      "featured": false
    },
    {
      "name": "St. Charles Pet Store Group",
      "category": "Pet Store",
      "address": "Lewis and Clark Village, MO",
      "phone": "",
      "email": "",
      "website": "",
      "hours": "",
      "rating": null,
      "review_count": null,
      "claimed": false,
      "featured": false
    },
    {
      "name": "Lewis and Clark Village Spa Services",
      "category": "Spa",
      "address": "Lewis and Clark Village, MO",
      "phone": "",
      "email": "",
      "website": "",
      "hours": "",
      "rating": null,
      "review_count": null,
      "claimed": false,
      "featured": false
    },
    {
      "name": "Lewis and Clark Village Paving Co",
      "category": "Paving",
      "address": "Lewis and Clark Village, MO",
      "phone": "",
      "email": "",
      "website": "",
      "hours": "",
      "rating": null,
      "review_count": null,
      "claimed": false,
      "featured": false
    },
    {
      "name": "Gateway Arch Temp Agency of Lewis and Clark Village",
      "category": "Temp Agency",
      "address": "Lewis and Clark Village, MO",
      "phone": "",
      "email": "",
      "website": "",
      "hours": "",
      "rating": null,
      "review_count": null,
      "claimed": false,
      "featured": false
    },
    {
      "name": "St. Charles Sign Shop Pro",
      "category": "Sign Shop",
      "address": "Lewis and Clark Village, MO",
      "phone": "",
      "email": "",
      "website": "",
      "hours": "",
      "rating": null,
      "review_count": null,
      "claimed": false,
      "featured": false
    },
    {
      "name": "Lewis and Clark Village Physical Therapy Center",
      "category": "Physical Therapy",
      "address": "Lewis and Clark Village, MO",
      "phone": "",
      "email": "",
      "website": "",
      "hours": "",
      "rating": null,
      "review_count": null,
      "claimed": false,
      "featured": false
    }
  ]
}