{
  "name": "Maupin",
  "state": "Oregon",
  "state_abbr": "OR",
  "county": "Wasco",
  "population": 432,
  "slug": "maupin-or",
  "businesses": [
    {
      "name": "High Desert Hotel of Maupin",
      "category": "Hotel",
      "address": "Maupin, OR",
      "phone": "",
      "email": "",
      "website": "",
      "hours": "",
      "rating": null,
      "review_count": null,
      "claimed": false,
      "featured": false
    },
    {
      "name": "Heritage Insurance Agency of Maupin",
      "category": "Insurance Agency",
      "address": "Maupin, OR",
      "phone": "",
      "email": "",
      "website": "",
      "hours": "",
      "rating": null,
      "review_count": null,
      "claimed": false,
      "featured": false
    },
    {
      "name": "Wasco Coffee Shop Pro",
      "category": "Coffee Shop",
      "address": "Maupin, OR",
      "phone": "",
      "email": "",
      "website": "",
      "hours": "",
      "rating": null,
      "review_count": null,
      "claimed": false,
      "featured": false
    },
    {
      "name": "Maupin Cleaning Service Express",
      "category": "Cleaning Service",
      "address": "Maupin, OR",
      "phone": "",
      "email": "",
      "website": "",
      "hours": "",
      "rating": null,
      "review_count": null,
      "claimed": false,
      "featured": false
    },
    {
      "name": "Wasco Barber Shop Center",
      "category": "Barber Shop",
      "address": "Maupin, OR",
      "phone": "",
      "email": "",
      "website": "",
      "hours": "",
      "rating": null,
      "review_count": null,
      "claimed": false,
      "featured": false
    },
    {
      "name": "Maupin Roofing Inc",
      "category": "Roofing",
      "address": "Maupin, OR",
      "phone": "",
      "email": "",
      "website": "",
      "hours": "",
      "rating": null,
      "review_count": null,
      "claimed": false,
      "featured": false
    },
    {
      "name": "Coastal Security Company Solutions",
      "category": "Security Company",
      "address": "Maupin, OR",
      "phone": "",
      "email": "",
      "website": "",
      "hours": "",
      "rating": null,
      "review_count": null,
      "claimed": false,
      "featured": false
    },
    {
      "name": "Heritage Towing Service Express",
      "category": "Towing Service",
      "address": "Maupin, OR",
      "phone": "",
      "email": "",
      "website": "",
      "hours": "",
      "rating": null,
      "review_count": null,
      "claimed": false,
      "featured": false
    },
    {
      "name": "Maupin Printing Shop Pro",
      "category": "Printing Shop",
      "address": "Maupin, OR",
      "phone": "",
      "email": "",
      "website": "",
      "hours": "",
      "rating": null,
      "review_count": null,
      "claimed": false,
      "featured": false
    },
    {
      "name": "Cascade Windows Center",
      "category": "Windows",
      "address": "Maupin, OR",
      "phone": "",
      "email": "",
      "website": "",
      "hours": "",
      "rating": null,
      "review_count": null,
      "claimed": false,
      "featured": false
    }
  ]
}